justanunsuspectingmodule/__init__.py
justanunsuspectingmodule/model_class.py
justanunsuspectingmodule-0.3.dist-info/LICENSE
justanunsuspectingmodule-0.3.dist-info/METADATA
justanunsuspectingmodule-0.3.dist-info/WHEEL
justanunsuspectingmodule-0.3.dist-info/top_level.txt
justanunsuspectingmodule-0.3.dist-info/RECORD
